dig_ass_chat_protos/DigitalAssistantChatManager_pb2.py
dig_ass_chat_protos/DigitalAssistantChatManager_pb2.pyi
dig_ass_chat_protos/DigitalAssistantChatManager_pb2_grpc.py
dig_ass_chat_protos/__init__.py
dig_ass_chat_protos/client.py
dig_ass_chat_protos-5.0.7.dist-info/METADATA
dig_ass_chat_protos-5.0.7.dist-info/WHEEL
dig_ass_chat_protos-5.0.7.dist-info/top_level.txt
dig_ass_chat_protos-5.0.7.dist-info/RECORD
