Metadata-Version: 2.4
Name: dig_ass_chat_protos
Version: 5.0.7
Summary: Proto files for dig_ass_chat_protos
Author: AGI-MED-TEAM
Requires-Python: >=3.11
Requires-Dist: agi-med-protos==2.2.0
